Workbook

Sheet RESUMEN
A1: BARATUSS — ANÁLISIS DE PUNTO DE EQUILIBRIO (BREAK-EVEN)
A2: Basado únicamente en datos reales registrados de BARATUSS. Los valores marcados como ESTIMACIÓN son editables.
A4: CONCLUSIÓN
A5: BARATUSS NECESITA VENDER
A6: EQUIVALE APROXIMADAMENTE A
A7: POR SEMANA
A8: POR DÍA
A9: CON EL RITMO ACTUAL | B9: SIN VENTAS REGISTRADAS (0 órdenes en Supabase) — no alcanzaría aún
A10: FECHA/MES ESTIMADO PARA ALCANZARLO | B10: NO DETERMINABLE — no hay ventas reales para proyectar
A11: PARA LLEGAR MÁS RÁPIDO | B11: Ver hoja ACCIONES (priorizar productos de alto margen, reducir costos fijos)
A13: ⚠️ DATOS FALTANTES (no inventados — ver hoja DATOS FALTANTES)
A14: • Costos fijos mensuales (alquiler, internet, etc.) NO registrados
A15: • Empaque: NO registrado
A16: • Publicidad: NO registrada
A17: • Ventas reales: 0 órdenes — sin historial para proyectar escenarios reales

Sheet COSTOS
A1: ANÁLISIS DE COSTOS — BARATUSS
A2: Solo datos reales. Celdas amarillas = editable (ESTIMACIÓN). Celdas rojas = dato faltante.
A4: COSTOS FIJOS MENSUALES (no dependen de las ventas)
A5: Alquiler/local | C5: DATO FALTANTE — no registrado
A6: Internet | C6: DATO FALTANTE — no registrado
A7: Bolsas/empaque (mensual) | C7: DATO FALTANTE — no registrado
A8: Publicidad/marketing | C8: DATO FALTANTE — no registrado
A9: Otros fijos | C9: DATO FALTANTE — no registrado
A10: TOTAL COSTOS FIJOS MENSUALES | B10: =SUM(B5:B9)
A12: COSTOS VARIABLES (por unidad vendida)
A13: Costo de adquisición (lo que cuesta el producto) | C13: DATO FALTANTE — varía por producto (ver hoja PRODUCTOS)
A14: Empaque por unidad | C14: DATO FALTANTE — no registrado
A15: Comisión Wompi (tarjeta) | B15: 0.0525 | C15: 5.25% del monto + $0.25 por transacción — dato real
A16: Tarifa fija Wompi por transacción | B16: 0.25 | C16: Dato real
A17: Envío/transporte | C17: DATO FALTANTE — el cobro al cliente es $2.50, pero el costo real de envío no está registrado

Sheet PRODUCTOS
A1: ANÁLISIS DE PRODUCTOS Y MÁRGENES — BARATUSS
A2: Precio base = lo que recibe BARATUSS (sin IVA ni comisión). Margen de contribución = precio base − costo variable.
A4: Producto | B4: Categoría | C4: Costo unitario | D4: Precio base (recibe BARATUSS) | E4: Precio final (cliente paga) | F4: Ganancia bruta/unidad | G4: Margen de ganancia | H4: Margen de contribución/unidad | I4: Fuente
A5: Camiseta negra | B5: Ropa | C5: 3 | D5: 4.5 | E5: =IF($D5="","",ROUND($D5*1.189325+0.25,2)) | F5: =IF(OR($C5="",$D5=""),"",$D5-$C5) | G5: =IF($D5="","",($D5-$C5)/$D5) | H5: =IF(OR($C5="",$D5=""),"",$D5-$C5) | I5: Dato real — inventario Supabase
A6: Camisa básica | B6: Ropa | C6: 3 | D6: 6 | E6: =IF($D6="","",ROUND($D6*1.189325+0.25,2)) | F6: =IF(OR($C6="",$D6=""),"",$D6-$C6) | G6: =IF($D6="","",($D6-$C6)/$D6) | H6: =IF(OR($C6="",$D6=""),"",$D6-$C6) | I6: Catálogo (ejemplo plantilla)
A7: Aritos (12 pares) | B7: Accesorios | C7: 0.125 | D7: 2.315 | E7: =IF($D7="","",ROUND($D7*1.189325+0.25,2)) | F7: =IF(OR($C7="",$D7=""),"",$D7-$C7) | G7: =IF($D7="","",($D7-$C7)/$D7) | H7: =IF(OR($C7="",$D7=""),"",$D7-$C7) | I7: Catálogo (ejemplo plantilla)
A8: Labial | B8: Maquillaje | E8: =IF($D8="","",ROUND($D8*1.189325+0.25,2)) | F8: =IF(OR($C8="",$D8=""),"",$D8-$C8) | G8: =IF($D8="","",($D8-$C8)/$D8) | H8: =IF(OR($C8="",$D8=""),"",$D8-$C8) | I8: DATO FALTANTE — sin costo registrado
A10: PROMEDIO (solo productos con datos) | C10: =IFERROR(AVERAGE(C5:C8),"") | D10: =IFERROR(AVERAGE(D5:D8),"") | F10: =IFERROR(AVERAGE(F5:F8),"") | G10: =IFERROR(AVERAGE(G5:G8),"") | H10: =IFERROR(AVERAGE(H5:H8),"")

Sheet BREAK-EVEN
A1: CÁLCULO DEL PUNTO DE EQUILIBRIO
A2: Fórmula: Break-even en unidades = Costos fijos mensuales ÷ Margen de contribución promedio por unidad
A4: Datos de entrada
A5: Costos fijos mensuales ($) | B5: =COSTOS!B10
A6: Margen de contribución promedio ($/unidad) | B6: =IFERROR(PRODUCTOS!H9,"")
A7: Precio de venta promedio ($/unidad, base) | B7: =IFERROR(PRODUCTOS!D9,"")
A8: Precio final promedio (cliente paga) | B8: =IFERROR(PRODUCTOS!E9,"")
A10: RESULTADOS
A11: A. Break-even en unidades/mes | B11: =IF($B$6=0,"",ROUNDUP($B$5/$B$6,0))
A12: B. Break-even en dólares/mes | B12: =IF($B$11="","",$B$11*$B$8)
A13: C. Transacciones/clientes aprox./mes | B13: =IF($B$11="","",ROUNDUP($B$11/1.5,0))
A14: (asume ~1.5 productos por transacción — ESTIMACIÓN)
A16: Explicación del cálculo
A17: • Margen de contribución promedio = promedio de (precio base − costo) de los productos con datos registrados.
A18: • Si los costos fijos están en $0 (no registrados), el break-even será $0 — necesita costos reales.
A19: • El resultado depende del margen promedio: al vender más productos de alto margen (aritos), el break-even baja.

Sheet ESCENARIOS
A1: ESCENARIOS MENSUALES — BARATUSS
A2: Sin ventas reales registradas, los escenarios son ESTIMACIONES editables (celdas amarillas) basadas en la capacidad de la tienda.
A4: Escenario | B4: Unidades/mes (editable) | C4: Ingresos (precio final) | D4: Costos variables | E4: Costos fijos | F4: Ganancia/Pérdida | G4: ¿Alcanza break-even? | H4: Déficit para break-even
A5: Conservador | B5: 5 | C5: =IF($B5="","",$B5*PRODUCTOS!$E$9) | D5: =IF($B5="","",$B5*PRODUCTOS!$C$9) | E5: =BREAK-EVEN!$B$5 | F5: =IF($C5="","",$C5-$D5-$E5) | G5: =IF($F5="","",IF($F5>=0,"✅ SÍ","❌ NO")) | H5: =IF($F5="","",IF($F5<0,ABS($F5),0)) | I5: Ventas bajas — arranque lento
A6: Realista | B6: 15 | C6: =IF($B6="","",$B6*PRODUCTOS!$E$9) | D6: =IF($B6="","",$B6*PRODUCTOS!$C$9) | E6: =BREAK-EVEN!$B$5 | F6: =IF($C6="","",$C6-$D6-$E6) | G6: =IF($F6="","",IF($F6>=0,"✅ SÍ","❌ NO")) | H6: =IF($F6="","",IF($F6<0,ABS($F6),0)) | I6: Ritmo razonable de tienda pequeña
A7: Optimista | B7: 40 | C7: =IF($B7="","",$B7*PRODUCTOS!$E$9) | D7: =IF($B7="","",$B7*PRODUCTOS!$C$9) | E7: =BREAK-EVEN!$B$5 | F7: =IF($C7="","",$C7-$D7-$E7) | G7: =IF($F7="","",IF($F7>=0,"✅ SÍ","❌ NO")) | H7: =IF($F7="","",IF($F7<0,ABS($F7),0)) | I7: Crecimiento fuerte con publicidad

Sheet PROYECCIÓN
A1: PROYECCIÓN MENSUAL HASTA EL BREAK-EVEN
A2: Proyección basada en unidades editables (amarillo) y costos reales. Sin ventas reales previas, esto es un escenario, no una predicción.
A4: Mes | B4: Unidades (editable) | C4: Ventas | D4: Ingresos | E4: Costos | F4: Ganancia/Pérdida | G4: Acumulado | H4: Estado
A5: Mes 1 | B5: 5 | C5: =IF($B5="","",$B5*PRODUCTOS!$E$9) | D5: =IF($B5="","",$B5*PRODUCTOS!$D$9) | E5: =IF($B5="","",$B5*PRODUCTOS!$C$9+BREAK-EVEN!$B$5) | F5: =IF($C5="","",$C5-$E5) | G5: =IF($F5="","",$F5) | H5: =IF($F5="","",IF($F5>=0,"✅ Break-even","⬇️ Por debajo"))
A6: Mes 2 | B6: 8 | C6: =IF($B6="","",$B6*PRODUCTOS!$E$9) | D6: =IF($B6="","",$B6*PRODUCTOS!$D$9) | E6: =IF($B6="","",$B6*PRODUCTOS!$C$9+BREAK-EVEN!$B$5) | F6: =IF($C6="","",$C6-$E6) | G6: =IF($F6="","",$F6+$G5) | H6: =IF($F6="","",IF($F6>=0,"✅ Break-even","⬇️ Por debajo"))
A7: Mes 3 | B7: 10 | C7: =IF($B7="","",$B7*PRODUCTOS!$E$9) | D7: =IF($B7="","",$B7*PRODUCTOS!$D$9) | E7: =IF($B7="","",$B7*PRODUCTOS!$C$9+BREAK-EVEN!$B$5) | F7: =IF($C7="","",$C7-$E7) | G7: =IF($F7="","",$F7+$G6) | H7: =IF($F7="","",IF($F7>=0,"✅ Break-even","⬇️ Por debajo"))
A8: Mes 4 | B8: 12 | C8: =IF($B8="","",$B8*PRODUCTOS!$E$9) | D8: =IF($B8="","",$B8*PRODUCTOS!$D$9) | E8: =IF($B8="","",$B8*PRODUCTOS!$C$9+BREAK-EVEN!$B$5) | F8: =IF($C8="","",$C8-$E8) | G8: =IF($F8="","",$F8+$G7) | H8: =IF($F8="","",IF($F8>=0,"✅ Break-even","⬇️ Por debajo"))
A9: Mes 5 | B9: 15 | C9: =IF($B9="","",$B9*PRODUCTOS!$E$9) | D9: =IF($B9="","",$B9*PRODUCTOS!$D$9) | E9: =IF($B9="","",$B9*PRODUCTOS!$C$9+BREAK-EVEN!$B$5) | F9: =IF($C9="","",$C9-$E9) | G9: =IF($F9="","",$F9+$G8) | H9: =IF($F9="","",IF($F9>=0,"✅ Break-even","⬇️ Por debajo"))
A10: Mes 6 | B10: 18 | C10: =IF($B10="","",$B10*PRODUCTOS!$E$9) | D10: =IF($B10="","",$B10*PRODUCTOS!$D$9) | E10: =IF($B10="","",$B10*PRODUCTOS!$C$9+BREAK-EVEN!$B$5) | F10: =IF($C10="","",$C10-$E10) | G10: =IF($F10="","",$F10+$G9) | H10: =IF($F10="","",IF($F10>=0,"✅ Break-even","⬇️ Por debajo"))
A11: Mes 7 | B11: 20 | C11: =IF($B11="","",$B11*PRODUCTOS!$E$9) | D11: =IF($B11="","",$B11*PRODUCTOS!$D$9) | E11: =IF($B11="","",$B11*PRODUCTOS!$C$9+BREAK-EVEN!$B$5) | F11: =IF($C11="","",$C11-$E11) | G11: =IF($F11="","",$F11+$G10) | H11: =IF($F11="","",IF($F11>=0,"✅ Break-even","⬇️ Por debajo"))
A12: Mes 8 | B12: 25 | C12: =IF($B12="","",$B12*PRODUCTOS!$E$9) | D12: =IF($B12="","",$B12*PRODUCTOS!$D$9) | E12: =IF($B12="","",$B12*PRODUCTOS!$C$9+BREAK-EVEN!$B$5) | F12: =IF($C12="","",$C12-$E12) | G12: =IF($F12="","",$F12+$G11) | H12: =IF($F12="","",IF($F12>=0,"✅ Break-even","⬇️ Por debajo"))
A13: Mes 9 | B13: 30 | C13: =IF($B13="","",$B13*PRODUCTOS!$E$9) | D13: =IF($B13="","",$B13*PRODUCTOS!$D$9) | E13: =IF($B13="","",$B13*PRODUCTOS!$C$9+BREAK-EVEN!$B$5) | F13: =IF($C13="","",$C13-$E13) | G13: =IF($F13="","",$F13+$G12) | H13: =IF($F13="","",IF($F13>=0,"✅ Break-even","⬇️ Por debajo"))
A14: Mes 10 | B14: 35 | C14: =IF($B14="","",$B14*PRODUCTOS!$E$9) | D14: =IF($B14="","",$B14*PRODUCTOS!$D$9) | E14: =IF($B14="","",$B14*PRODUCTOS!$C$9+BREAK-EVEN!$B$5) | F14: =IF($C14="","",$C14-$E14) | G14: =IF($F14="","",$F14+$G13) | H14: =IF($F14="","",IF($F14>=0,"✅ Break-even","⬇️ Por debajo"))
A15: Mes 11 | B15: 40 | C15: =IF($B15="","",$B15*PRODUCTOS!$E$9) | D15: =IF($B15="","",$B15*PRODUCTOS!$D$9) | E15: =IF($B15="","",$B15*PRODUCTOS!$C$9+BREAK-EVEN!$B$5) | F15: =IF($C15="","",$C15-$E15) | G15: =IF($F15="","",$F15+$G14) | H15: =IF($F15="","",IF($F15>=0,"✅ Break-even","⬇️ Por debajo"))
A16: Mes 12 | B16: 45 | C16: =IF($B16="","",$B16*PRODUCTOS!$E$9) | D16: =IF($B16="","",$B16*PRODUCTOS!$D$9) | E16: =IF($B16="","",$B16*PRODUCTOS!$C$9+BREAK-EVEN!$B$5) | F16: =IF($C16="","",$C16-$E16) | G16: =IF($F16="","",$F16+$G15) | H16: =IF($F16="","",IF($F16>=0,"✅ Break-even","⬇️ Por debajo"))

Sheet ACCIONES
A1: ¿QUÉ TIENE QUE HACER BARATUSS PARA LLEGAR AL BREAK-EVEN?
A3: PRODUCTOS A PRIORIZAR
A4: • Aritos (margen 94.6%) → venderlos primero, son tu mayor margen.
A5: • Camisa básica (margen 50%) → segundo lugar.
A6: • Labial: registrar su costo para saber su margen (dato faltante).
A8: PRECIOS
A9: • Los precios actuales SÍ cubren costo + comisión Wompi + IVA (fórmula 1.189325+0.25).
A10: • Verificar que el precio final no ahuyente: $3.00 (aritos) es accesible; $7.39 (camisa) está bien.
A11: • Considerar precios psicológicos ($2.99, $7.49) si el margen lo permite.
A13: COSTOS A REDUCIR
A14: • Sin costos fijos registrados — primero hay que REGISTRARLOS (dato faltante).
A15: • Empaque: comprar en volumen para bajar costo por unidad.
... A24: • Más productos por transacción = menos transacciones necesarias para el break-even.

Sheet DATOS FALTANTES
A1: INFORMACIÓN QUE NECESITO PARA UN ANÁLISIS CONFIABLE
A2: Estos datos NO están registrados. Sin ellos, el break-even no es exacto. Por favor complétalos.
A4: Costos fijos mensuales | B4: Alquiler, internet, luz, etc. | C4: ¿Cuánto pagas al mes por tu negocio?
A5: Empaque por unidad | B5: Bolsas, cajas, etiquetas | C5: ¿Cuánto cuesta empacar 1 producto?
A6: Publicidad/marketing | B6: Anuncios, promociones | C6: ¿Cuánto inviertes en publicidad?
A7: Envío real | B7: Transporte para entregas | C7: ¿Cuánto te cuesta un envío de verdad?
A8: Costo del labial | B8: Precio de compra del labial | C8: ¿A cuánto compras cada labial?
A9: Ventas reales | B9: Historial de pedidos | C9: La tienda tiene 0 órdenes — necesita primeras ventas
A10: Ticket promedio real | B10: Productos por compra | C10: ¿Cuántos productos compra un cliente típico?
